{"cameraMode":{"drawMode":0,"name":"Shaded","section":"Shading Mode"},"sceneLighting":true,"audioPlay":false,"sceneViewState":{"showFog":true,"showMaterialUpdate":false,"showSkybox":true,"showFlares":true,"showImageEffects":true,"showParticleSystems":true},"in2DMode":false,"pivot":{"x":2.2541136741638185,"y":-0.03055592253804207,"z":4.528149127960205},"rotation":{"x":0.009430233389139176,"y":0.8750579953193665,"z":0.017065556719899179,"w":-0.48362526297569277},"size":0.7724096179008484,"orthographic":false}